pywnp/__init__.py
pywnp/pywnp.py
pywnp-2.0.2.dist-info/LICENSE
pywnp-2.0.2.dist-info/METADATA
pywnp-2.0.2.dist-info/WHEEL
pywnp-2.0.2.dist-info/top_level.txt
pywnp-2.0.2.dist-info/RECORD
