Metadata-Version: 2.1
Name: pywnp
Version: 2.0.2
Summary: A python library to communicate with the WebNowPlaying-Redux browser extension
Author-email: keifufu <pypi@keifufu.dev>
License: Copyright 2023 keifufu
Project-URL: Homepage, https://github.com/keifufu/PyWNP
Project-URL: Bug Tracker, https://github.com/keifufu/PyWNP/issues
Keywords: webnowplaying,wnp,youtube,spotify,media,music
Classifier: Programming Language :: Python :: 3
Classifier: License :: OSI Approved :: MIT License
Classifier: Operating System :: OS Independent
Requires-Python: >=3.7
License-File: LICENSE
Requires-Dist: aiohttp
Requires-Dist: winsdk ; platform_system == "Windows"
